google_drive_sync/__init__.py
google_drive_sync/download.py
google_drive_sync/upload.py
gdsync666-0.0.2.dist-info/LICENSE
gdsync666-0.0.2.dist-info/METADATA
gdsync666-0.0.2.dist-info/WHEEL
gdsync666-0.0.2.dist-info/top_level.txt
gdsync666-0.0.2.dist-info/RECORD
