Metadata-Version: 2.1
Name: gdsync666
Version: 0.0.2
Summary: Bidirectionally sync your local folder with a one from Google Drive
Author-email: Daniil Chalov <cyber.barrista@gmail.com>
License: Copyright (c) 2012-2023 Scott Chacon and others
Project-URL: Homepage, https://github.com/cyber-barrista/gdsync
Keywords: Google Drive,sync,upload,download
Classifier: License :: OSI Approved :: MIT License
Classifier: Programming Language :: Python
Classifier: Programming Language :: Python :: 3
Classifier: Typing :: Typed
Classifier: Intended Audience :: Developers
Classifier: Intended Audience :: Information Technology
Classifier: Intended Audience :: System Administrators
Requires-Python: >=3.9
License-File: LICENSE
Requires-Dist: google-api-python-client (>=2.89.0)
Requires-Dist: google-auth-oauthlib (>=1.0.0)
Requires-Dist: oauth2client (>=4.1.3)
Provides-Extra: dev
Requires-Dist: black ; extra == 'dev'
Requires-Dist: bumpver ; extra == 'dev'
Requires-Dist: isort ; extra == 'dev'
Requires-Dist: pip-tools ; extra == 'dev'
Requires-Dist: pytest ; extra == 'dev'
